pybfs/__init__.py
pybfs/bfs.py
pybfs/calibrate.py
pybfs/plot.py
pybfs/utilities.py
pybfs-0.1.1.dist-info/LICENSE
pybfs-0.1.1.dist-info/METADATA
pybfs-0.1.1.dist-info/WHEEL
pybfs-0.1.1.dist-info/top_level.txt
pybfs-0.1.1.dist-info/RECORD
