Metadata-Version: 2.1
Name: pybfs
Version: 0.1.1
Summary: Python Baseflow Separation - A physically-based baseflow separation algorithm for hydrological analysis
Author: BYU Hydroinformatics
License: MIT
Project-URL: Homepage, https://github.com/BYU-Hydroinformatics/pybfs
Project-URL: Documentation, https://github.com/BYU-Hydroinformatics/pybfs
Project-URL: Repository, https://github.com/BYU-Hydroinformatics/pybfs
Project-URL: Issues, https://github.com/BYU-Hydroinformatics/pybfs/issues
Keywords: hydrology,baseflow,baseflow separation,streamflow,groundwater
Classifier: Development Status :: 4 - Beta
Classifier: Intended Audience :: Science/Research
Classifier: Topic :: Scientific/Engineering
Classifier: License :: OSI Approved :: MIT License
Classifier: Programming Language :: Python :: 3
Classifier: Programming Language :: Python :: 3.7
Classifier: Programming Language :: Python :: 3.8
Classifier: Programming Language :: Python :: 3.9
Classifier: Programming Language :: Python :: 3.10
Classifier: Programming Language :: Python :: 3.11
Classifier: Programming Language :: Python :: 3.12
Requires-Python: >=3.7
License-File: LICENSE
Requires-Dist: numpy (>=1.19.0)
Requires-Dist: pandas (>=1.1.0)
Requires-Dist: matplotlib (>=3.3.0)
Requires-Dist: numba (>=0.56.0)
Requires-Dist: scipy (>=1.5.0)
Requires-Dist: statsmodels (>=0.13.0)
Provides-Extra: dev
Requires-Dist: pytest (>=6.0) ; extra == 'dev'
Requires-Dist: pytest-cov (>=2.0) ; extra == 'dev'
Provides-Extra: docs
Requires-Dist: mkdocs (>=1.5.0) ; extra == 'docs'
Requires-Dist: mkdocs-material (>=9.4.0) ; extra == 'docs'
Requires-Dist: mkdocstrings[python] (>=0.24.0) ; extra == 'docs'
Requires-Dist: pymdown-extensions (>=10.0) ; extra == 'docs'
